anyloop/__init__.py
anyloop-0.1.0.dist-info/LICENSE
anyloop-0.1.0.dist-info/METADATA
anyloop-0.1.0.dist-info/WHEEL
anyloop-0.1.0.dist-info/top_level.txt
anyloop-0.1.0.dist-info/RECORD
