Metadata-Version: 2.1
Name: anyloop
Version: 0.1.0
Summary: Async Loop in Sync Function
Home-page: https://github.com/LanceLovereading/anyloop-project
Author: Lance Li
Author-email: lancelovereading@gmail.com
Keywords: async,comprehension,loop
License-File: LICENSE
